qutiepy.py
QutiePy-0.2.4.dist-info/LICENSE
QutiePy-0.2.4.dist-info/METADATA
QutiePy-0.2.4.dist-info/WHEEL
QutiePy-0.2.4.dist-info/top_level.txt
QutiePy-0.2.4.dist-info/RECORD
