Metadata-Version: 2.1
Name: QutiePy
Version: 0.2.4
Summary: A simple package for learning about and exploring quantum computing.
Home-page: UNKNOWN
Author: T. E. L. Findlay
Author-email: findlaytel@gmail.com
License: MIT
Platform: UNKNOWN
Classifier: Development Status :: 3 - Alpha
Classifier: Intended Audience :: Education
Classifier: Programming Language :: Python :: 3
Requires-Dist: numpy
Requires-Dist: scipy
